efb_online_middleware/__init__.py
efb_online_middleware/__version__.py
efb_online_middleware-0.0.5.dist-info/LICENSE
efb_online_middleware-0.0.5.dist-info/METADATA
efb_online_middleware-0.0.5.dist-info/WHEEL
efb_online_middleware-0.0.5.dist-info/entry_points.txt
efb_online_middleware-0.0.5.dist-info/top_level.txt
efb_online_middleware-0.0.5.dist-info/RECORD
